README.md
setup.py
pyserialui/__init__.py
pyserialui/examplehandler.py
pyserialui/interpreter.py
pyserialui/overrides.py
pyserialui/shell.py
pyserialui/sqliteauth.py
pyserialui/types.py
pyserialui/wrappers.py
pyserialui.egg-info/PKG-INFO
pyserialui.egg-info/SOURCES.txt
pyserialui.egg-info/dependency_links.txt
pyserialui.egg-info/top_level.txt
pyserialui/debug/SerialUI.py
pyserialui/debug/__init__.py
pyserialui/examples/__init__.py
pyserialui/examples/barebones.py
pyserialui/examples/fulldemo.py