Metadata-Version: 2.1
Name: pyserialui
Version: 1.0.0
Summary: SerialUI druid support and examples
Home-page: https://github.com/psychogenic/pyserialui
Author: Pat Deegan
Author-email: pyserialui-contact@devicedruid.com
License: UNKNOWN
Download-URL: https://github.com/psychogenic/pyserialui/archive/v1.0.0.tar.gz
Platform: UNKNOWN
Classifier: Programming Language :: Python :: 3
Classifier: Development Status :: 4 - Beta
Classifier: License :: OSI Approved :: GNU Lesser General Public License v3 (LGPLv3)
Classifier: Operating System :: OS Independent
Classifier: Topic :: Terminals :: Serial
